sqlalchemy_bigid/__init__.py
sqlalchemy_bigid/config.py
sqlalchemy_bigid/migration.py
sqlalchemy_bigid/schema.py
sqlalchemy_bigid/types.py
sqlalchemy_bigid/utils.py
sqlalchemy_bigid/version.py
sqlalchemy_postgres_bigid-0.1.2.dist-info/LICENSE
sqlalchemy_postgres_bigid-0.1.2.dist-info/METADATA
sqlalchemy_postgres_bigid-0.1.2.dist-info/WHEEL
sqlalchemy_postgres_bigid-0.1.2.dist-info/top_level.txt
sqlalchemy_postgres_bigid-0.1.2.dist-info/RECORD
